CHANGES.txt
README.txt
bootstrap.py
buildout.cfg
setup.py
src/zope/__init__.py
src/zope.modulealias.egg-info/PKG-INFO
src/zope.modulealias.egg-info/SOURCES.txt
src/zope.modulealias.egg-info/dependency_links.txt
src/zope.modulealias.egg-info/namespace_packages.txt
src/zope.modulealias.egg-info/not-zip-safe
src/zope.modulealias.egg-info/requires.txt
src/zope.modulealias.egg-info/top_level.txt
src/zope/modulealias/DEPENDENCIES.cfg
src/zope/modulealias/README.txt
src/zope/modulealias/__init__.py
src/zope/modulealias/meta.zcml
src/zope/modulealias/metaconfigure.py
src/zope/modulealias/metadirectives.py
src/zope/modulealias/tests/__init__.py
src/zope/modulealias/tests/dummymodule.py
src/zope/modulealias/tests/test_modulealias.py
